README
setup.py
linseed/__init__.py
linseed/app.py
linseed/battery.py
linseed/cpu.py
linseed/current_time.py
linseed/exceptions.py
linseed/info_source_manager.py
linseed/memory.py
linseed/parsing.py
linseed/partition.py
linseed/read.py
linseed/stat.py
linseed/util.py
linseed/wicd.py
linseed.egg-info/PKG-INFO
linseed.egg-info/SOURCES.txt
linseed.egg-info/dependency_links.txt
linseed.egg-info/entry_points.txt
linseed.egg-info/requires.txt
linseed.egg-info/top_level.txt
linseed/test/__init__.py
linseed/test/battery_test.py
linseed/test/cpu_test.py
linseed/test/info_source_manager_test.py
linseed/test/memory_test.py
linseed/test/partition_test.py
linseed/test/testsuite.py
linseed/test/wicd_test.py