Metadata-Version: 1.0
Name: linseed
Version: 0.4
Summary: Gather and print linux system information.
Home-page: http://code.google.com/p/linseed/
Author: Austin Bingham
Author-email: austin.bingham@gmail.com
License: MIT
Keywords: system info resources
Platform: UNKNOWN
